{
	"name_reference" : "drake",
	"cn_reference" : "deleike",
	"nameJP" : "ドレイク",
	"nameCN" : "德雷克",
	"ID" : "P014",
	"name" : "Drake",
	"internal_id" : "299041",
	"rarity" : "Decisive",
	"initialStar" : "★★★☆☆☆",
	"hull" : "Heavy Cruiser",
	"navy" : "Royal Navy",
	"prefix" : "HMS",
	"buildTime" : "N/A",
	"voiceActress" : "Asami Imai",
	"parameters": {
		"firepower" : "",
		"torpedo" : "",
		"aviation" : "",
		"evasion" : "",
		"antiAir" : "",
		"hp" : ""
	},
	"scrap": {
		"gold" : "9",
		"oil" : "3",
		"medal" : "30"
	},
	"releaseDate": {
		"JP" : "July 9, 2020",
		"CN" : "July 9, 2020",
		"KR" : "July 9, 2020",
		"EN" : "July 9, 2020"
	},
	"artist": {
		"name" : "",
		"weibo" : "",
		"twitter" : "",
		"pixiv" : "",
		"other" : ""
	},
	"enhance": {
		"firepower" : "0",
		"torpedo" : "0",
		"aviation" : "0",
		"reload" : "0"
	},
	"acquisitionMethod" : "Research and Development",
	"skill": {
		"1" : {
			"icon" : "19290",
			"requirement" : "Default Unlocked",
			"name" : "The Fearless Privateer",
			"type" : "Offensive",
			"description" : "Increases this ship's built-in Secondary Gun Crit Rate by 20.0% (50.0%) and gives a LV.1 (Lv.10) ammo buff to it. When this ship uses a Main Gun that fires Normal or HE ammo: this ship's Main Gun ammo type changes to special HE (DMG is based on the skill's level.)"
		},
		"2" : {
			"icon" : "19300",
			"requirement" : "Default Unlocked",
			"name" : "Flintlock Burst",
			"type" : "Support",
			"description" : "Every 30 (20)1s: fires a special barrage that heals this ship for 15.0% of the DMG dealt (barrage DMG is based on the skill's level.) When this ship sinks an enemy: increases this ship's FP and RLD by 1.0% (5.0%) until the end of the battle. Can be stacked up to 3 times."
		},
		"3" : {
			"icon" : "19000",
			"requirement" : "Strenghten Level 10 (I) / Level 20 (II) / Level 30 (III)",
			"name" : "Siren Killer Ⅰ",
			"type" : "Offensive",
			"description" : "Increases this ship's DMG to Sirens by 5.0%."
		},
		"4" : {
			"icon" : "29561",
			"requirement" : "Strenghten Level 10 (I) / Level 30 (III)",
			"name" : "All Out Assault Ⅰ",
			"type" : "Offensive",
			"description" : "Activates All Out Assault Ⅰ: Drake once every 12 times the Main Guns are fired."
		}
	},
	"skin": {
		"1" : {
			"id" : "deleike",
			"name" : "Drake",
			"description" : "Heavy cruiser – Drake. ",
			"expression" : {
				"0" : {
					"id" : "0"
				},
				"1" : {
					"id" : "1"
				},
				"2" : {
					"id" : "2"
				},
				"3" : {
					"id" : "3"
				},
				"4" : {
					"id" : "4"
				},
				"5" : {
					"id" : "5"
				},
				"6" : {
					"id" : "6"
				}
			}
		}
	},
	"defaultEquipment": {
		"1" : {
			"icon" : "",
			"rarity" : "",
			"name" : ""
		},
		"2" : {
			"icon" : "",
			"rarity" : "",
			"name" : ""
		},
		"3" : {
			"icon" : "",
			"rarity" : "",
			"name" : ""
		}
	},
	"stats": {
		"base": {
			"hp" : "970",
			"firepower" : "54",
			"torpedo" : "46",
			"antiAir" : "54",
			"aviation" : "0",
			"reload" : "51",
			"hit" : "48",
			"evasion" : "6",
			"speed" : "26.6",
			"luck" : "0",
			"asw" : "0",
			"oxygen" : "0",
			"ammo" : "0",
			"cost" : "",
			"armor" : "Medium"
		},
		"100": {
			"hp" : "3511",
			"firepower" : "254",
			"torpedo" : "213",
			"antiAir" : "169",
			"aviation" : "0",
			"reload" : "120",
			"hit" : "125",
			"evasion" : "15",
			"speed" : "26.6",
			"luck" : "0",
			"asw" : "0",
			"oxygen" : "0",
			"ammo" : "0",
			"cost" : "15",
			"armor" : "Medium"
		},
		"120": {
			"hp" : "4163",
			"firepower" : "289",
			"torpedo" : "245",
			"antiAir" : "204",
			"aviation" : "0",
			"reload" : "139",
			"hit" : "145",
			"evasion" : "59",
			"speed" : "26.6",
			"luck" : "0",
			"asw" : "0",
			"oxygen" : "0",
			"ammo" : "0",
			"cost" : "15",
			"armor" : "Medium"
		},
		"100retrofit": {
			"hp" : "",
			"firepower" : "",
			"torpedo" : "",
			"antiAir" : "",
			"aviation" : "",
			"reload" : "",
			"hit" : "",
			"evasion" : "",
			"speed" : "26.6",
			"luck" : "0",
			"asw" : "",
			"oxygen" : "0",
			"ammo" : "0",
			"cost" : "15",
			"armor" : "Medium"
		},
		"120retrofit": {
			"hp" : "",
			"firepower" : "",
			"torpedo" : "",
			"antiAir" : "",
			"aviation" : "",
			"reload" : "",
			"hit" : "",
			"evasion" : "",
			"speed" : "26.6",
			"luck" : "0",
			"asw" : "",
			"oxygen" : "0",
			"ammo" : "0",
			"cost" : "15",
			"armor" : "Medium"
		}
	},
	"strengthenLevel": {
		"level5" : "HP +237/Anti-Air +13/Evasion +5/Main gun base +1",
		"level10": "Unlock EX Barrage Ⅰ/Main gun efficiency +5%/Limit Break ★★★★☆☆",
		"level15" : "HP +473/Anti-Air +27/Preload torpedo +1/Main gun efficiency +10%",
		"level20": "Torpedo efficiency +10%/Limit Break ★★★★★☆",
		"level25" : "HP +710/Anti-Air +40/Evasion +10",
		"level30": "Improve EX Barrage/Main gun efficiency +15%/Limit Break ★★★★★★"
	},
	"equipmentLoadout": {
		"1": {
			"type": "Heavy Cruiser",
			"efficiency": "100%/105%/105%/120%",
			"amount": "1/2/2/2",
			"preload": "0/0/0/0"
		},
		"2": {
			"type": "Torpedo",
			"efficiency": "110%/110%/120%/120%",
			"amount": "1/1/1/1",
			"preload": "0/0/1/1"
		},
		"3": {
			"type": "Anti-Air Gun",
			"efficiency": "125%/125%/125%/125%",
			"amount": "1/1/1/1",
			"preload": "0/0/0/0"
		},
		"4": {
			"type": "Auxilary",
			"efficiency": "-",
			"amount": "-",
			"preload": "-"
		},
		"5": {
			"type": "Auxilary",
			"efficiency": "-",
			"amount": "-",
			"preload": "-"
		}
	},
	"build": {
		"light": {
			"JP": "",
			"CN": "",
			"EN": ""
		},
		"heavy": {
			"JP": "",
			"CN": "",
			"EN": ""
		},
		"special": {
			"JP": "",
			"CN": "",
			"EN": ""
		},
		"limited": {
			"JP": "",
			"CN": "",
			"EN": ""
		}
	},
	"drop": {
		"droppable": "false",
		"list": {
			"1": {
				"event": "",
				"chapter": {
					"1": {
						"label": "Ch .1",
						"node": {
							"1": {
								"drop": "✓",
								"note": "-"
							}
						}
					}
				}
			}
		}
	},
	"lines": {
		"skin": {
			"1": {
				"skin_id" : "deleike",
				"id" : "0",
				"label" : "Drake",
				"dialogue" : {
					"1" : {
						"event" : "Ship Description",
						"media" : "",
						"chinese" : "重巡洋舰-—德雷克",
						"chineseTL" : "",
						"chineseNote" : "",
						"japanese" : "重巡洋艦・ドレイク",
						"japaneseTL" : "",
						"japaneseNote" : "",
						"english" : "Heavy cruiser – Drake.",
						"englishNote" : ""
					},
					"2" : {
						"event" : "Biography",
						"media" : "profile",
						"chinese" : "我是皇家海军的重巡洋舰·德雷克。也许你对我的存在还感到比较陌生，不过没关系，在以后的战斗里，我的9.2寸炮会给你留下足够充分的深刻印象的！",
						"chineseTL" : "",
						"chineseNote" : "",
						"japanese" : "ロイヤルネイビー所属の重巡ドレイクよ。あたしのことが分からないというのなら、あたしの9.2インチ砲がこれからの戦いで分からせてあげる！",
						"japaneseTL" : "",
						"japaneseNote" : "",
						"english" : "I'm the Royal Navy heavy cruiser, Drake. If you weren't aware of my existence before, I'll make sure you know now by showing you the power of my 9.2 inch guns!",
						"englishNote" : ""
					},
					"3" : {
						"event" : "Acquisition",
						"media" : "get",
						"chinese" : "你就是指挥官吧？看起来不错~皇家海军重巡德雷克，现在加入你的麾下！姑且问一句，出击的许可，应该已经准备好了吧？",
						"chineseTL" : "",
						"chineseNote" : "",
						"japanese" : "あんたが指揮官か？中々骨のある奴ね。ロイヤルネイビー所属・重巡ドレイク、今日からあんたの艦隊に加わってあげる。念の為に聞いておくけど、出撃はもちろんさせてくれるわよね？",
						"japaneseTL" : "",
						"japaneseNote" : "",
						"english" : "So you're the Commander? Seems you've got some backbone. I'm the Royal Navy heavy cruiser, Drake, and I'll be joining your fleet. Just making sure, you will deploy me, right?",
						"englishNote" : ""
					},
					"4" : {
						"event" : "Login",
						"media" : "login",
						"chinese" : "来了啊。今天先做点什么？先研究下作战也好，要直接先出击也是没问题的哦？",
						"chineseTL" : "",
						"chineseNote" : "",
						"japanese" : "さあ来たわね。今日は何から始める？作戦を考えるのもいいけど、先に出撃してもいいわよ？",
						"japaneseTL" : "",
						"japaneseNote" : "",
						"english" : "You've finally come. What should we start with today? It's great to think about battle plans and all, but how about sending me on a sortie first?",
						"englishNote" : ""
					},
					"5" : {
						"event" : "Details",
						"media" : "detail",
						"chinese" : "任何伟大的事迹都必定有它的起点，但惟有坚持到最后才能获得真正的荣耀——所以继续努力吧！",
						"chineseTL" : "",
						"chineseNote" : "",
						"japanese" : "すべての偉業には始まりがある。しかし最後までやり続けなければ真の栄光はない。――というわけで、引き続き頑張りなさい",
						"japaneseTL" : "",
						"japaneseNote" : "",
						"english" : "All great odysseys must begin somewhere, but true glory only awaits those who reach their destination... That's why you ought to stay your course until the very end!",
						"englishNote" : ""
					},
					"6" : {
						"event" : "Main 1",
						"media" : "main_1",
						"chinese" : "武装舰船的是装甲、火炮和鱼雷，而武装人的，则是胆识、见识与学识。",
						"chineseTL" : "",
						"chineseNote" : "",
						"japanese" : "艦船は装甲と兵装――つまり火砲と魚雷で武装する、人は胆力と知力――つまり見識と知識で武装するってわけね",
						"japaneseTL" : "",
						"japaneseNote" : "",
						"english" : "Basically, ships arm themselves with armor and equipment—in other words, with artillery and torpedoes. Meanwhile, humans arm themselves with courage and intelligence—in other words, with perception and wisdom.",
						"englishNote" : ""
					},
					"7" : {
						"event" : "Main 2",
						"media" : "main_2",
						"chinese" : "我不讨厌礼节，也不反对适当的仪式感，不过，繁文缛节的东西，能少点还是尽量少点好。",
						"chineseTL" : "",
						"chineseNote" : "",
						"japanese" : "マナーとかセレモニーとか、嫌いではないけど、シンプルに越したことはないわよ",
						"japaneseTL" : "",
						"japaneseNote" : "",
						"english" : "While I don't hate customs and ceremony, I do prefer the simpler things.",
						"englishNote" : ""
					},
					"8" : {
						"event" : "Main 3",
						"media" : "main_3",
						"chinese" : "比起榨好的苹果汁，还是沾着露水的新鲜苹果更诱人，你也是这么觉得的吧！",
						"chineseTL" : "",
						"chineseNote" : "",
						"japanese" : "ジュースより…こう朝露の滴る生の果物がいいわね。あんたもそう思わない？",
						"japaneseTL" : "",
						"japaneseNote" : "",
						"english" : "The dew-kissed fruit of the morning makes for the best juice. Don't you agree?",
						"englishNote" : ""
					},
					"9" : {
						"event" : "Touch",
						"media" : "touch_1",
						"chinese" : "我喜欢直白的人，所以有什么事尽管直接说出来就好。",
						"chineseTL" : "",
						"chineseNote" : "",
						"japanese" : "はっきりしてる人とは気が合うわよ、あたし。あんたも言いたいことがあればはっきり言いなさいな",
						"japaneseTL" : "",
						"japaneseNote" : "",
						"english" : "I tend to get along better with people who are straightforward. If there's something you want to say to me, say it clearly.",
						"englishNote" : ""
					},
					"10" : {
						"event" : "Touch (Special)",
						"media" : "touch_2",
						"chinese" : "嚯~？你胆子还不小嘛~！",
						"chineseTL" : "",
						"chineseNote" : "",
						"japanese" : "はーん？あんた、いい度胸じゃない",
						"japaneseTL" : "",
						"japaneseNote" : "",
						"english" : "Huuh? You sure have some guts.",
						"englishNote" : ""
					},
					"11" : {
						"event" : "Mission",
						"media" : "task",
						"chinese" : "按部就班地做任务可不是我的风格，嗯…先看看有多少报酬吧！",
						"chineseTL" : "",
						"chineseNote" : "",
						"japanese" : "地味な任務をやるなんてあたしらしくもないね。うっ……これ、どんな報酬が貰えるか確認してみない？",
						"japaneseTL" : "",
						"japaneseNote" : "",
						"english" : "Doing mundane tasks is totally not my style. Um... Why don't we check the rewards first?",
						"englishNote" : ""
					},
					"12" : {
						"event" : "Mission Complete",
						"media" : "mission_complete",
						"chinese" : "虽然任务报酬还不少，不过像这样由上面施予的奖励总感觉少了点什么呢…",
						"chineseTL" : "",
						"chineseNote" : "",
						"japanese" : "任務報酬はまあまあいいけど、こう「報酬を貰う」だけじゃなーんか物足りないわね",
						"japaneseTL" : "",
						"japaneseNote" : "",
						"english" : "Can't complain about the bounty, but I just feel like there's \"something\" missing.",
						"englishNote" : ""
					},
					"13" : {
						"event" : "Mail",
						"media" : "mail",
						"chinese" : "信件，会不会发现了哪里有宝藏的消息呢，哈哈。",
						"chineseTL" : "",
						"chineseNote" : "",
						"japanese" : "手紙よ。お宝の情報が舞い込んだりするとかない？",
						"japaneseTL" : "",
						"japaneseNote" : "",
						"english" : "Here, a letter for you. Anybody find information on some treasure?",
						"englishNote" : ""
					},
					"14" : {
						"event" : "Return to Port",
						"media" : "home",
						"chinese" : "作战辛苦了，正好我准备了些新鲜的葡萄，要来一颗吗？…那好，接好了！嘿！",
						"chineseTL" : "",
						"chineseNote" : "",
						"japanese" : "作戦お疲れ様。新鮮な果物……ぶどうでもどう？ふふ、ちゃんとキャッチしてみせろよ～？それ！",
						"japaneseTL" : "",
						"japaneseNote" : "",
						"english" : "Nice job, Commander. How would you like some fresh... grapes? Hehe, come on~ don't drop 'em!",
						"englishNote" : ""
					},
					"15" : {
						"event" : "Commission Complete",
						"media" : "expedition",
						"chinese" : "果然老老实实地做委托没有直接从敌人手里掠夺来得过瘾啊…啊，没什么。",
						"chineseTL" : "",
						"chineseNote" : "",
						"japanese" : "軍事委託とかで地道に配給物を調達するより、敵から物資を奪ったほうが…なんでもないわっ",
						"japaneseTL" : "",
						"japaneseNote" : "",
						"english" : "Instead of collecting supplies like this, wouldn't it be better to just raid the enemy for... Actually, never mind.",
						"englishNote" : ""
					},
					"16" : {
						"event" : "Enhancement",
						"media" : "upgrade",
						"chinese" : "感觉炮管能发出更让人愉快的声音了，哈哈！",
						"chineseTL" : "",
						"chineseNote" : "",
						"japanese" : "主砲がもっといい感じに響くようになったじゃない！はははは！",
						"japaneseTL" : "",
						"japaneseNote" : "",
						"english" : "Now that's the kind of sound I want to hear from my main guns! Ahahaha!",
						"englishNote" : ""
					},
					"17" : {
						"event" : "Flagship",
						"media" : "warcry",
						"chinese" : "哼哼哼，放开了大干一场吧！",
						"chineseTL" : "",
						"chineseNote" : "",
						"japanese" : "よぉし、派手にぶちかますわよ！",
						"japaneseTL" : "",
						"japaneseNote" : "",
						"english" : "Alright, let's do this with fanfare!",
						"englishNote" : ""
					},
					"18" : {
						"event" : "Victory",
						"media" : "mvp",
						"chinese" : "胜利，无论何时都让人倍感愉快啊，哈哈！",
						"chineseTL" : "",
						"chineseNote" : "",
						"japanese" : "勝利、全くいつだって愉快な気分にさせてくれるわ！",
						"japaneseTL" : "",
						"japaneseNote" : "",
						"english" : "Victory always leaves you feeling nice and refreshed!",
						"englishNote" : ""
					},
					"19" : {
						"event" : "Defeat",
						"media" : "lose",
						"chinese" : "今天的所有屈辱，我都会铭记在心的…走着瞧吧！",
						"chineseTL" : "",
						"chineseNote" : "",
						"japanese" : "今日の屈辱…絶対に忘れないからね！そっちも覚えていなさい！",
						"japaneseTL" : "",
						"japaneseNote" : "",
						"english" : "How humiliating... I'll get you back for this! Just you wait!",
						"englishNote" : ""
					},
					"20" : {
						"event" : "Skill",
						"media" : "skill",
						"chinese" : "可别怪我无情了！",
						"chineseTL" : "",
						"chineseNote" : "",
						"japanese" : "手は抜かないわ！",
						"japaneseTL" : "",
						"japaneseNote" : "",
						"english" : "You won't find any mercy here!",
						"englishNote" : ""
					},
					"21" : {
						"event" : "Low HP",
						"media" : "hp",
						"chinese" : "嘁，对面的有两下子嘛！",
						"chineseTL" : "",
						"chineseNote" : "",
						"japanese" : "ちっ、やってくれる…！",
						"japaneseTL" : "",
						"japaneseNote" : "",
						"english" : "Ugh, they got me!",
						"englishNote" : ""
					},
					"22" : {
						"event" : "Affinity (Upset)",
						"media" : "feeling1",
						"chinese" : "若只是几次无心之过，我是不会放在心上的，但如果你还是这样一意孤行，那就别怪我不留情面了。",
						"chineseTL" : "",
						"chineseNote" : "",
						"japanese" : "わざとじゃなければ数回ぐらいは見逃してやるけど、あんたがこのままヘマし続けるならぶっ飛ばしてやるわよ",
						"japaneseTL" : "",
						"japaneseNote" : "",
						"english" : "I am willing to turn a blind eye to a few accidents, but if you keep doing this intentionally, don't expect any mercy from me.",
						"englishNote" : ""
					},
					"23" : {
						"event" : "Affinity (Stranger)",
						"media" : "feeling2",
						"chinese" : "战场上无需拘泥于手段，无论是靠小伎俩，还是正面进攻，站到最后的胜者才有资格谈论正义，如此而已。",
						"chineseTL" : "",
						"chineseNote" : "",
						"japanese" : "戦いはなんでもありよ。正々堂々でも搦め手でも、勝ったほうが正義を語れるわ",
						"japaneseTL" : "",
						"japaneseNote" : "",
						"english" : "Everything goes on the battlefield. Whether you fight fair-and-square or use backhanded methods, it matters not. History is written by the victors.",
						"englishNote" : ""
					},
					"24" : {
						"event" : "Affinity (Friendly)",
						"media" : "feeling3",
						"chinese" : "你对冒险也有兴趣吗？太好了，我正愁缺个伴呢，说吧，你想要的是寻找大海中的黄金秘宝，还是探寻远方的神秘国度？",
						"chineseTL" : "",
						"chineseNote" : "",
						"japanese" : "そういえば指揮官って遠洋航海…もとい、冒険に興味ある？ちょうど仲間を募集しているところなの。興味があるならお宝でも未開の大地でもなんでも狙ってみるつもりよ",
						"japaneseTL" : "",
						"japaneseNote" : "",
						"english" : "Oh right, Commander. Did you have any interest in navigation... or rather, adventure? I've been recruiting mates. If you're interested, let's go look for treasure or uninhabited islands or something!",
						"englishNote" : ""
					},
					"25" : {
						"event" : "Affinity (Like)",
						"media" : "feeling4",
						"chinese" : "唔…一起探险是挺好的，不过，最近出去的地方是不是都太近了点？不是港区内就是近海……老实说，有点无趣啊。下次，我带你去大海更深的地方吧？",
						"chineseTL" : "",
						"chineseNote" : "",
						"japanese" : "二人っきりで出かけるのはいいけど、ご近所ってのが多すぎない？母港や周りの海域ばかりで……ふぅ、正直こうしていてもドキドキしないし、次からはあたしがもっと遠い場所に連れてってあげる",
						"japaneseTL" : "",
						"japaneseNote" : "",
						"english" : "Sure, it's great to travel together and all, but aren't all these places too close by? Port, the surrounding areas, and the nearby ocean... Sigh. Honestly, going to these places doesn't make me excited at all. Next time, I'm taking you somewhere farther away.",
						"englishNote" : ""
					},
					"26" : {
						"event" : "Affinity (Love)",
						"media" : "feeling5",
						"chinese" : "原来如此，你并不在乎旅行的终点，而更加在意同行的伙伴吗。也就是说，只要和我一起，无论去哪都没问题！是这样吧，哈哈哈…唔？等等，这意思不就是…",
						"chineseTL" : "",
						"chineseNote" : "",
						"japanese" : "なるほど、あんたにとっちゃ場所なんてどうでもよくて、あたしと一緒に出かけられさえすればどこでもいいと……ちょ、ちょっと待って…ははは…あんた、もしかして……",
						"japaneseTL" : "",
						"japaneseNote" : "",
						"english" : "I see. So what you're telling me is that it's not the place that matters, but that if I'm with you, anywhere is fine? ... Haha... W-Wait... are you saying...",
						"englishNote" : ""
					},
					"27" : {
						"event" : "Pledge",
						"media" : "propose",
						"chinese" : "你不觉得奇妙吗？这种既不是“被征服”也不是“不甘心”，单纯感到“羞耻”的感觉……都是因为你，我都变得不像我了。虽然我也不讨厌这样的状态…就是了。你能理解吗？",
						"chineseTL" : "",
						"chineseNote" : "",
						"japanese" : "あんたも変だと思わない？こう「心奪われた」でもなく「悔しい」でもなく、ただただ「恥ずかしい」って気持ち……もうあんたのせいであたしらしくなくなったじゃない！…別にこんな気持ち、嫌いじゃないけどさ…ね？分かってくれる？",
						"japaneseTL" : "",
						"japaneseNote" : "",
						"english" : "Don't you think it's strange too? This feeling that's not quite 'having my heart stolen' or 'feeling vexed,' but more just... 'feeling embarrassed'? ...Gosh, it's all your fault that I'm not acting like myself! ... But I don't quite hate this feeling either... Well? Do you get what I mean?",
						"englishNote" : ""
					},
					"28" : {
						"event" : "Easter Egg 1(Jean Bart)",
						"media" : "link1",
						"chinese" : "比比看谁能夺得更多的战果吧！",
						"chineseTL" : "",
						"chineseNote" : "",
						"japanese" : "どっちの戦果が上か競争よ！",
						"japaneseTL" : "",
						"japaneseNote" : "",
						"english" : "Let's see who's more useful!",
						"englishNote" : ""
					},
					"29" : {
						"event" : "Like Present",
						"media" : "present_like",
						"chinese" : "",
						"chineseTL" : "",
						"chineseNote" : "",
						"japanese" : "",
						"japaneseTL" : "",
						"japaneseNote" : "",
						"english" : "",
						"englishNote" : ""
					},
					"30" : {
						"event" : "Dislike Present",
						"media" : "present_dislike",
						"chinese" : "",
						"chineseTL" : "",
						"chineseNote" : "",
						"japanese" : "",
						"japaneseTL" : "",
						"japaneseNote" : "",
						"english" : "",
						"englishNote" : ""
					},
					"31" : {
						"event" : "Main Title",
						"media" : "extra",
						"chinese" : "",
						"chineseTL" : "",
						"chineseNote" : "",
						"japanese" : "",
						"japaneseTL" : "",
						"japaneseNote" : "",
						"english" : "",
						"englishNote" : ""
					}
				}
			}
		}
	}
}
