{
	"name_reference": "haruna",
	"cn_reference": "zhenming",
	"nameJP": "榛名",
	"nameCN": "榛名",
	"ID": "206",
	"name": "Haruna",
	"internal_id": "304031",
	"rarity": "Elite",
	"initialStar": "★★☆☆☆",
	"hull": "Battlecruiser",
	"navy": "Sakura Empire",
	"prefix": "IJN",
	"buildTime": "N/A",
	"class": "Kongou-Class",
	"voiceActress": "Sayaka Harada",
	"parameters": {
		"firepower": "A",
		"torpedo": "E",
		"aviation": "E",
		"evasion": "C",
		"antiAir": "C",
		"hp": "B"
	},
	"scrap": {
		"gold": "10",
		"oil": "3",
		"medal": "4"
	},
	"releaseDate": {
		"JP": "May 31, 2018",
		"CN": "June 7, 2018",
		"KR": "",
		"EN": ""
	},
	"artist": {
		"name": "Criin",
		"weibo": "https://weibo.com/cirini",
		"twitter": "https://twitter.com/hanasa_criin",
		"pixiv": "https://www.pixiv.net/member.php?id=4460847",
		"other": ""
	},
	"enhance": {
		"firepower": "46",
		"torpedo": "0",
		"aviation": "0",
		"reload": "11"
	},
	"acquisitionMethod": "Available in Point Shop in event \"Ink-Stained Steel Sakura\"",
	"skill": {
		"1": {
			"icon": "11340",
			"requirement": "Default Unlocked",
			"name": "Warship of the Dawn's Radiance",
			"type": "Offensive",
			"description": "Every time the main gun is fired, increases own firepower and AA by 1.5% (6%). Can be stacked up to 4 times."
		}
	},
	"skin": {
		"1": {
			"id": "zhenming",
			"name": "Haruna ",
			"description": "Kongou-class fast battleship number four – Haruna. ",
			"expression": {
				"0": {
					"id": "0"
				},
				"1" : {
					"id" : "1"
				},
				"2" : {
					"id" : "2"
				},
				"3" : {
					"id" : "3"
				},
				"4" : {
					"id" : "4"
				}
			}
		},
		"2": {
			"id": "zhenming_2",
			"name": "Free Time Before Class ",
			"description": "I think it's fine to enjoy school life once in a while... Hm? You wanna know what I'm listening to? Sure, if you're okay with just one earbud. ",
			"expression": {
				"0": {
					"id": "0"
				}
			}
		}
	},
	"defaultEquipment": {
		"1": {
			"icon": "36500",
			"rarity": "Common",
			"name": "76mm AA Gun"
		},
		"2": {
			"icon": "",
			"rarity": "",
			"name": ""
		}
	},
	"stats": {
		"100": {
			"hp": "5620",
			"firepower": "320",
			"torpedo": "0",
			"antiAir": "238",
			"aviation": "0",
			"reload": "138",
			"hit": "55",
			"evasion": "20",
			"speed": "30",
			"luck": "47",
			"asw": "0",
			"oxygen": "0",
			"ammo": "0",
			"cost": "14",
			"armor": "Medium"
		},
		"120": {
			"hp": "6604",
			"firepower": "360",
			"torpedo": "0",
			"antiAir": "273",
			"aviation": "0",
			"reload": "159",
			"hit": "68",
			"evasion": "37",
			"speed": "30",
			"luck": "47",
			"asw": "0",
			"oxygen": "0",
			"ammo": "0",
			"cost": "14",
			"armor": "Medium"
		},
		"base": {
			"hp": "1087",
			"firepower": "68",
			"torpedo": "0",
			"antiAir": "51",
			"aviation": "0",
			"reload": "58",
			"hit": "21",
			"evasion": "8",
			"speed": "30",
			"luck": "47",
			"asw": "0",
			"oxygen": "0",
			"ammo": "0",
			"cost": "5",
			"armor": "Medium"
		},
		"100retrofit": {
			"hp": "",
			"firepower": "",
			"torpedo": "",
			"antiAir": "",
			"aviation": "",
			"reload": "",
			"hit": "",
			"evasion": "",
			"speed": "30",
			"luck": "47",
			"asw": "",
			"oxygen": "0",
			"ammo": "0",
			"cost": "14",
			"armor": "Medium"
		},
		"120retrofit": {
			"hp": "",
			"firepower": "",
			"torpedo": "",
			"antiAir": "",
			"aviation": "",
			"reload": "",
			"hit": "",
			"evasion": "",
			"speed": "30",
			"luck": "47",
			"asw": "",
			"oxygen": "0",
			"ammo": "0",
			"cost": "14",
			"armor": "Medium"
		}
	},
	"limitBreak": {
		"tier1": "Main Gun Mount +1 / Main Gun Efficiency +5%",
		"tier2": "Secondary Gun Mount +2 / Main Gun Efficiency +10%",
		"tier3": "Main Gun Mount +1 / Main Gun Efficiency +15%"
	},
	"equipmentLoadout": {
		"1": {
			"type": "Battleship",
			"efficiency": "105%/110%/120%/135%",
			"amount": "1/1/1/1",
			"preload": "0/0/0/0"
		},
		"2": {
			"type": "Light Cruiser",
			"efficiency": "150%/150%/150%/150%",
			"amount": "1/1/3/3",
			"preload": "0/0/0/0"
		},
		"3": {
			"type": "Anti-Air Gun",
			"efficiency": "90%/90%/90%/90%",
			"amount": "1/1/1/1",
			"preload": "0/0/0/0"
		},
		"4": {
			"type": "Auxiliary",
			"efficiency": "-",
			"amount": "-",
			"preload": "-"
		},
		"5": {
			"type": "Auxiliary",
			"efficiency": "-",
			"amount": "-",
			"preload": "-"
		}
	},
	"build": {
		"light": {
			"JP": "-",
			"CN": "-",
			"EN": "-"
		},
		"heavy": {
			"JP": "-",
			"CN": "-",
			"EN": "-"
		},
		"special": {
			"JP": "-",
			"CN": "-",
			"EN": "-"
		},
		"limited": {
			"JP": "-",
			"CN": "-",
			"EN": "-"
		}
	},
	"drop": {
		"droppable": "false",
		"list": {
			"1": {
				"event": "",
				"chapter": {
					"1": {
						"label": "Ch .1",
						"node": {
							"1": {
								"drop": "✓",
								"note": "-"
							}
						}
					}
				}
			}
		}
	},
	"lines": {
		"skin": {
			"1": {
				"skin_id": "zhenming",
				"id": "0",
				"label": "Haruna ",
				"dialogue": {
					"1": {
						"event": "Ship Description",
						"media": "",
						"chinese": "金刚级高速战舰三番舰—榛名",
						"chineseTL": "Third ship of the Kongou class fast battleships, Haruna.",
						"chineseNote": "",
						"japanese": "金剛型高速戦艦三番艦・榛名",
						"japaneseTL": "Third ship of the Kongou-class Fast Battleships, Haruna.",
						"japaneseNote": "",
						"english": "Kongou-class fast battleship number four – Haruna.",
						"englishNote": ""
					},
					"2": {
						"event": "Biography",
						"media": "profile",
						"chinese": "重樱航速最快的，同时也是唯一一艘直到最后都在奋战的高速战舰——武勋舰榛名。这一次，我也会——努力尽情尽力地战斗！",
						"chineseTL": "I am the fastest, and the only fast battleship that fought til the very end, decorated battleship Haruna. This time, I will also fight with everything I have!",
						"chineseNote": "",
						"japanese": "重桜高速戦艦最速にして、最後まで奮戦した金剛型三番艦・榛名。今回も――全身全霊、全力で戦ってみせる！",
						"japaneseTL": "I am Haruna, the third ship of the Kongou-class and the fastest of the Sakura Empire battleships. This time too, I'll fight to the end with all my spirit and might!",
						"japaneseNote": "",
						"english": "I'm Haruna, the Sakura Empire's speediest fast battleship. I fought hard till the very end. Once more, I will fight with all my heart, holding nothing back!",
						"englishNote": ""
					},
					"3": {
						"event": "Acquisition",
						"media": "get",
						"chinese": "初次见面，我是重樱首艘高速战舰——榛名。指挥官，比起刀剑，我更喜欢拳头唷",
						"chineseTL": "Nice to meet you, I am the first Sakura Empire fast battleship , Haruna. Commander, I actually prefer fists over swords.",
						"chineseNote": "",
						"japanese": "初めまして、重桜初の高速戦艦・榛名と言います。刀より拳を好む性分ですが、何卒よろしく",
						"japaneseTL": "Hello, I am Haruna, one of the first fast battleships of the Sakura Empire. I'm someone who prefers the fist to the sword. Nice to meet you.",
						"japaneseNote": "",
						"english": "Hello. I'm the Sakura Empire's latest fast battleship, Haruna. I prefer to use my fists over my blade, but I hope that won't be an issue.",
						"englishNote": ""
					},
					"4": {
						"event": "Login",
						"media": "login",
						"chinese": "这么爽朗的天气，不出海实在太可惜了，对吧，指挥官",
						"chineseTL": "Such great weather, isn't it a waste to not sail out today? Right, commander?",
						"chineseNote": "",
						"japanese": "いい天気だよね。「せっかくの晴天なんだから出航すればよかった」なんてことにならない方がいいよ。指揮官もそう思うよね？",
						"japaneseTL": "The weather is good today, though I would not prefer leaving the dock because \"it would be a shame not to with such fine weather.\" Don't you agree, Commander?",
						"japaneseNote": "",
						"english": "Nice weather today. We should head out so we don't miss our chance to enjoy it. Don't you agree, Commander?",
						"englishNote": ""
					},
					"5": {
						"event": "Details",
						"media": "detail",
						"chinese": "我也…想像雾岛那样受人欢迎呢…",
						"chineseTL": "I also...want to be as popular as Kirishima...",
						"chineseNote": "",
						"japanese": "私も霧島みたいな人気者になりたい……かな……",
						"japaneseTL": "I guess I also want to become someone popular like Kirishima.",
						"japaneseNote": "",
						"english": "I wish I was as popular as Kirishima... Well, kind of...",
						"englishNote": ""
					},
					"6": {
						"event": "Main 1",
						"media": "main_1",
						"chinese": "终于有能和威尔士以拳交心的机会了！",
						"chineseTL": "I finally got the chance to exchange blows with Wales!",
						"chineseNote": "",
						"japanese": "ようやく…ようやくウェールズと戦える…！",
						"japaneseTL": "Finally, finally I can fight against Wales!",
						"japaneseNote": "",
						"english": "At last... At long last, I will have my battle with Wales...!",
						"englishNote": ""
					},
					"7": {
						"event": "Main 2",
						"media": "main_2",
						"chinese": "指挥官，没有勇气和毅力战胜不了的敌人，你也是这么认为的吧？",
						"chineseTL": "Commander, without perseverance and courage it's impossible to triumph over your enemies, don't you think so as well?",
						"chineseNote": "",
						"japanese": "勇気と根性で勝てない相手なんていないよ。指揮官もそう思わない？",
						"japaneseTL": "There are no insurmountable opponents with bravery and determination. Don't you agree, Commander?",
						"japaneseNote": "",
						"english": "When you've got bravery and willpower, no enemy is insurmountable. Isn't that right, Commander?",
						"englishNote": ""
					},
					"8": {
						"event": "Main 3",
						"media": "main_3",
						"chinese": "牛肉果然还是上州的最好——指挥官，你也尝尝吧？",
						"chineseTL": "When it comes to beef, it has to be Joushuu...commander, come try it as well.",
						"chineseNote": "",
						"japanese": "牛肉と言えば上州牛よね。指揮官も食べてみる？",
						"japaneseTL": "Speaking of beef, I recommend Joshu beef. Would Commander also want to try some?",
						"japaneseNote": "",
						"english": "Joushuu beef is some of the best around. Care to try some?",
						"englishNote": ""
					},
					"9": {
						"event": "Touch",
						"media": "touch_1",
						"chinese": "指挥官，你也喜欢吃比叡姐做的大福吗？",
						"chineseTL": "Commander, do you also like to eat Hiei's Daifuku?",
						"chineseNote": "",
						"japanese": "比叡さんの作った和三盆……指揮官も好き？",
						"japaneseTL": "Do you like the sugar sweets Hiei made, too?",
						"japaneseNote": "",
						"english": "Do you like Hiei's handmade sweets, too?",
						"englishNote": ""
					},
					"10": {
						"event": "Touch (Special)",
						"media": "touch_2",
						"chinese": "咦？带上手套，就不容易弄脏手了呀",
						"chineseTL": "Eh, the gloves? It's to prevent my hand from getting dirty when hitting you.",
						"chineseNote": "",
						"japanese": "は！……手袋をしていれば、今度殴る時に手を汚さずに済ませられそうね",
						"japaneseTL": "Ha! If I wore gloves, I won't have to dirty my hands hitting you next time.",
						"japaneseNote": "",
						"english": "Hah!!!... I'll keep my gloves on next time so I can strike you without getting my hands dirty.",
						"englishNote": ""
					},
					"11": {
						"event": "Mission",
						"media": "task",
						"chinese": "比叡姐，一起去活动活动筋骨怎么样？",
						"chineseTL": "Hiei, let's go exercise a little, shall we?",
						"chineseNote": "",
						"japanese": "比叡さん、一緒に体を動かしてみない？",
						"japaneseTL": "Hiei, want to go get some exercise?",
						"japaneseNote": "",
						"english": "Hiei, what do you say we get some exercise?",
						"englishNote": ""
					},
					"12": {
						"event": "Mission Complete",
						"media": "mission_complete",
						"chinese": "金刚姐，我也算能独当一面了吧？",
						"chineseTL": "Kongou, I am independent enough now.",
						"chineseNote": "",
						"japanese": "金剛姉さん、私はもう一人前ですよ？",
						"japaneseTL": "Big sis Kongou, I'm already grown-up, you know?",
						"japaneseNote": "",
						"english": "Kongou, I'm basically already an adult now.",
						"englishNote": ""
					},
					"13": {
						"event": "Mail",
						"media": "mail",
						"chinese": "我很喜欢你的嗓音，所以——能念给我听吗？",
						"chineseTL": "I really like your voice,so...could you read it for me?",
						"chineseNote": "",
						"japanese": "指揮官の声が好き。だから――読んでもらえないかな？",
						"japaneseTL": "I like hearing your voice, so won't you read it to me?",
						"japaneseNote": "",
						"english": "I like your voice, Commander. So... could you read this letter out loud for me?",
						"englishNote": ""
					},
					"14": {
						"event": "Return to Port",
						"media": "home",
						"chinese": "辛苦了，有遇上敌人吗？",
						"chineseTL": "Good work, did you encounter any enemies?",
						"chineseNote": "",
						"japanese": "お疲れ様。敵に会ったりした？",
						"japaneseTL": "Good work. Did you see any enemies?",
						"japaneseNote": "",
						"english": "Well done out there. Did you run into any enemies?",
						"englishNote": ""
					},
					"15": {
						"event": "Commission Complete",
						"media": "expedition",
						"chinese": "哎——还没轮到我出场！？",
						"chineseTL": "Eh, it's still not my turn yet?",
						"chineseNote": "",
						"japanese": "よし、次は私が――え…まだ…？",
						"japaneseTL": "Alright, it's time for me...eh, not yet?",
						"japaneseNote": "",
						"english": "All right, I should head out and... Huh...? Not yet...?",
						"englishNote": ""
					},
					"16": {
						"event": "Enhancement",
						"media": "upgrade",
						"chinese": "速度又变快了！",
						"chineseTL": "My speed has increased!",
						"chineseNote": "",
						"japanese": "速力、上昇！",
						"japaneseTL": "Max speed, boost!",
						"japaneseNote": "",
						"english": "I've become faster!",
						"englishNote": ""
					},
					"17": {
						"event": "Flagship",
						"media": "warcry",
						"chinese": "终于到我出场了！",
						"chineseTL": "It's finally my turn!",
						"chineseNote": "",
						"japanese": "さあ、始めるよ！",
						"japaneseTL": "Now, let's begin!",
						"japaneseNote": "",
						"english": "Let us begin!",
						"englishNote": ""
					},
					"18": {
						"event": "Victory",
						"media": "mvp",
						"chinese": "金刚姐，我要奖励！",
						"chineseTL": "Kongou, I want a reward!",
						"chineseNote": "",
						"japanese": "金剛姉さん！ご褒美が欲しいです！ ",
						"japaneseTL": "Big sis Kongou! I want a reward!",
						"japaneseNote": "",
						"english": "Kongou! Please reward me!",
						"englishNote": ""
					},
					"19": {
						"event": "Defeat",
						"media": "lose",
						"chinese": "咕……很抱歉，但输了就是输了——",
						"chineseTL": "Ke...I am very sorry, but a loss is a loss...",
						"chineseNote": "",
						"japanese": "くっ……ごめんなさい…でも、負けは負けだよね…",
						"japaneseTL": "Ugh, I'm sorry. But a loss is a loss.",
						"japaneseNote": "",
						"english": "Gah... I'm sorry, but... a loss is a loss...",
						"englishNote": ""
					},
					"20": {
						"event": "skill",
						"media": "skill",
						"chinese": "火力——全开！",
						"chineseTL": "Full power!",
						"chineseNote": "",
						"japanese": "火力――全開！！",
						"japaneseTL": "Firepower, full force!",
						"japaneseNote": "",
						"english": "Unleash more firepower!",
						"englishNote": ""
					},
					"21": {
						"event": "Low HP",
						"media": "hp",
						"chinese": "一切还没有结束！",
						"chineseTL": "Not all is lost yet!",
						"chineseNote": "",
						"japanese": "まだ終わりじゃないよ！",
						"japaneseTL": "It's not over!",
						"japaneseNote": "",
						"english": "It's not over yet!",
						"englishNote": ""
					},
					"22": {
						"event": "Affinity (Upset)",
						"media": "feeling1",
						"chinese": "死心吧——",
						"chineseTL": "Give up...",
						"chineseNote": "",
						"japanese": "望みを絶たれよ――",
						"japaneseTL": "You've let down my expectations.",
						"japaneseNote": "",
						"english": "I've lost all hope in you.",
						"englishNote": ""
					},
					"23": {
						"event": "Affinity (Stranger)",
						"media": "feeling2",
						"chinese": "金刚姐，我来帮你揉揉肩吧",
						"chineseTL": "Kongou, let me give you a massage.",
						"chineseNote": "",
						"japanese": "金剛姉さん、肩を揉ませてください",
						"japaneseTL": "Big sis Kongou, let me massage your shoulders.",
						"japaneseNote": "",
						"english": "Kongou, allow me to give you a shoulder massage.",
						"englishNote": ""
					},
					"24": {
						"event": "Affinity (Friendly)",
						"media": "feeling3",
						"chinese": "激战之后，就应该吃一桶热腾腾的大米饭呢",
						"chineseTL": "After an intense battle, having a pot of piping hot rice is the way to go.",
						"chineseNote": "",
						"japanese": "激戦のあとはバケツ盛り白ご飯が食べたくなるね",
						"japaneseTL": "A fierce battle makes me want to eat a bucket full of rice afterwards.",
						"japaneseNote": "",
						"english": "After a tough battle, I feel like eating a whole bucket full of rice.",
						"englishNote": ""
					},
					"25": {
						"event": "Affinity (Like)",
						"media": "feeling4",
						"chinese": "指挥官，你也会跳舞吗？嗯…那个——能教教我吗？",
						"chineseTL": "Commander, do you also know how to dance? Erm...could...could you teach me?",
						"chineseNote": "",
						"japanese": "指揮官はダンスも出来るの？ええと、その――私に踊り方を教えてくれないかな…？",
						"japaneseTL": "Do you know how to dance, Commander? Um, I wonder if you could teach me how to dance?",
						"japaneseNote": "",
						"english": "Can you dance, Commander? You see, um... I was wondering if you could teach me how to do it...",
						"englishNote": ""
					},
					"26": {
						"event": "Affinity (Love)",
						"media": "feeling5",
						"chinese": "指挥官，在比叡姐的宴会上，我能做你的舞伴吗？  ",
						"chineseTL": "Commander, can I be your dance partner at Hiei's banquet?",
						"chineseNote": "",
						"japanese": "指揮官、今度の比叡さんの宴会で、私にダンス相手を務めさせてもらえない……？",
						"japaneseTL": "Commander, the next time when Hiei hosts a party, would you be my dancing partner?",
						"japaneseNote": "",
						"english": "Commander, could I please be your dance partner for the next banquet Hiei is hosting...?",
						"englishNote": ""
					},
					"27": {
						"event": "Pledge",
						"media": "propose",
						"chinese": "有、有点害羞呢……现在，指挥官就是我最重要的人了……哎，和姐姐们比？那、那个，不一样的啦——",
						"chineseTL": "This is, slightly embarrassing...from now on, commander is the most important person in my life...Eh, what about my sisters? That, that is a different matter...",
						"chineseNote": "",
						"japanese": "す、少し恥ずかしいね……これからは指揮官が私の一番大切な人……あ、姉と比べるとどうかって？そ、そんなの全然違う話でしょ？！",
						"japaneseTL": "Th-this is a little embarrassing. From now on you are my most important person. Ah, how important are you compared to my older sister? Th-that's a totally different story, isn't it?!",
						"japaneseNote": "",
						"english": "T-this feels a little odd... From now on, you'll be my most beloved... H-how you \"compare to my big sisters\"? T-that's not at all what I was talking about!",
						"englishNote": ""
					},
					"28": {
						"event": "Easter Egg 1 (Kongou)",
						"media": "link1",
						"chinese": "金刚姐，我怎么样！？",
						"chineseTL": "(Kongou) Kongou, How did I do!",
						"chineseNote": "",
						"japanese": "金剛姉さん、私は活躍できていますか！？",
						"japaneseTL": "(Kongou) Big sis Kongou, did I do well!?",
						"japaneseNote": "",
						"english": "Kongou, am I doing well?!",
						"englishNote": ""
					},
					"29": {
						"event": "Easter Egg 2 (Hiei)",
						"media": "link2",
						"chinese": "我会将眼前的一切，都干净利落地——击溃！",
						"chineseTL": "(Hiei) I will crush everything before me!",
						"chineseNote": "",
						"japanese": "目の前の全てを……撃ち倒す！！",
						"japaneseTL": "(Hiei) Everything you see in front of us, shoot it down!!",
						"japaneseNote": "",
						"english": "All those before us... will fall!",
						"englishNote": ""
					},
					"30": {
						"event": "Easter Egg 3 (Kirishima)",
						"media": "link3",
						"chinese": "好好欣赏姐姐的英勇身姿吧！",
						"chineseTL": "(Kirishima) Just admire my valiant fighting!",
						"chineseNote": "",
						"japanese": "私の勇姿を見せてあげる！",
						"japaneseTL": "(Kirishima) I'll show you how dauntless I am!",
						"japaneseNote": "",
						"english": "Bear witness to my bravery!",
						"englishNote": ""
					},
					"31": {
						"event": "Easter Egg 4 (Ise, Hyuuga)",
						"media": "link4",
						"chinese": "吴港分队——出击！",
						"chineseTL": "(Ise, Hyuuga) Kure port division, sortieing!",
						"chineseNote": "",
						"japanese": "呉配属戦艦隊、進めっ！",
						"japaneseTL": "(Ise, Hyuuga) Kure-assigned Battleship Fleet, advance!",
						"japaneseNote": "",
						"english": "Kure Battleship Fleet, charge!",
						"englishNote": ""
					},
					"32": {
						"event": "Valentines 2019",
						"media": "",
						"chinese": "指挥官，给你，巧克力。不过先说好，是比叡姐帮我做的，我试了好多次都失败了。没办法，只有这个我是真的不拿手……",
						"chineseTL": "",
						"chineseNote": "",
						"japanese": "指揮官、ほら、チョコ。言っておくけど、これは私一人で作ったのではなく、比叡姉さんにも手伝ってもらったよ？…こういう手先の器用さが要る料理は私、やっぱり得意ではないから。",
						"japaneseTL": "",
						"japaneseNote": "",
						"english": "",
						"englishNote": ""
					}
				}
			},
			"2": {
				"skin_id": "zhenming_2",
				"id": "1",
				"label": "Free Time Before Class ",
				"dialogue": {
					"1": {
						"event": "Ship Description",
						"media": "",
						"chinese": "偶尔转换心情，享受一下校园生活似乎也不错…嗯？指挥官也想一起听歌吗？耳机分你一半——",
						"chineseTL": "It's pretty nice to have a change of pace, and enjoy school life once in a while...Hmm? Commander also wants to listen? Here, take this piece.",
						"chineseNote": "",
						"japanese": "たまには学園生活ってものを楽しんでもいい気がする…うん？自分も聞きたいって？いいよ。こっちの半分でよければ",
						"japaneseTL": "It's okay to enjoy school life once in a while. Hmm? You want to listen, too? Sure, I'll share with you.",
						"japaneseNote": "",
						"english": "I think it's fine to enjoy school life once in a while... Hm? You wanna know what I'm listening to? Sure, if you're okay with just one earbud.",
						"englishNote": ""
					},
					"2": {
						"event": "Acquisition",
						"media": "get_1",
						"chinese": "偶尔转换心情，享受一下校园生活似乎也不错…嗯？指挥官也想一起听歌吗？耳机分你一半——",
						"chineseTL": "It's pretty nice to have a change of pace, and enjoy school life once in a while...Hmm? Commander also wants to listen? Here, take this piece.",
						"chineseNote": "",
						"japanese": "たまには学園生活ってものを楽しんでもいい気がする…うん？自分も聞きたいって？いいよ。こっちの半分でよければ",
						"japaneseTL": "It's okay to enjoy school life once in a while. Hmm? You want to listen, too? Sure, I'll share with you.",
						"japaneseNote": "",
						"english": "I think it's fine to enjoy school life once in a while... Hm? You wanna know what I'm listening to? Sure, if you're okay with just one earbud.",
						"englishNote": ""
					},
					"3": {
						"event": "Details",
						"media": "detail_1",
						"chinese": "和雾岛走在一起时，总会引起过多的关注…哈啊…受欢迎也不净是好事啊……",
						"chineseTL": "Walking together with Kirishima always attracts so too much attention...Sigh...I guess being popular is not always a good thing...",
						"chineseNote": "",
						"japanese": "霧島と一緒にこういう恰好で出歩くと余計見られるようになる気がする……はあ…人気者も大変ね……",
						"japaneseTL": "I feel like I'm also getting stared at next to Kirishima in this outfit. Haah, those who are popular sure have it tough.",
						"japaneseNote": "",
						"english": "I think people will gawk at us if Kirishima and I walk around looking like this... *Sigh*... It's tough being popular...",
						"englishNote": ""
					},
					"4": {
						"event": "Main 1",
						"media": "main_1_1",
						"chinese": "比起坐在教室里听课，我还是更喜欢在操场活动身体呢…",
						"chineseTL": "Instead of studying in class, I think I prefer exercising in the courtyard...",
						"chineseNote": "",
						"japanese": "教室で授業を受けるより、運動場で汗をかく方が好きかな",
						"japaneseTL": "Instead of studying in class, I think I prefer exercising and breaking a sweat.",
						"japaneseNote": "",
						"english": "I think I prefer working up a sweat in the sports field over reading in the classroom.",
						"englishNote": ""
					},
					"5": {
						"event": "Main 2",
						"media": "main_2_1",
						"chinese": "社团活动啊…空手道部之类的…怎么样？",
						"chineseTL": "Clubs huh...How about...ones like Karate club?",
						"chineseNote": "",
						"japanese": "部活は…空手部ってのは…どう？",
						"japaneseTL": "Club activities, how about Karate club?",
						"japaneseNote": "",
						"english": "Gotta join a club... There's the karate club... Maybe that'll work?",
						"englishNote": ""
					},
					"6": {
						"event": "Main 3",
						"media": "main_3_1",
						"chinese": "我这周有空哟，要不要一起去哪里逛逛呢，指挥官？",
						"chineseTL": "I'm free this week. Commander, want to go out somewhere?",
						"chineseNote": "",
						"japanese": "今週なら放課後は空いてるよ。指揮官、どっか行かない？",
						"japaneseTL": "I'm free this week after class. Commander, want to go out somewhere?",
						"japaneseNote": "",
						"english": "I'm free all week after school. Why don't we hang out a bit, Commander?",
						"englishNote": ""
					},
					"7": {
						"event": "Touch",
						"media": "touch_1_1",
						"chinese": "比叡姐做的便当，每天都很让人期待呢",
						"chineseTL": "I enjoy having Hiei's homemade bento everyday.",
						"chineseNote": "",
						"japanese": "比叡さんが作ってくれた弁当が毎日の楽しみなんだ",
						"japaneseTL": "I enjoy having Hiei's homemade lunchbox everyday.",
						"japaneseNote": "",
						"english": "I always look forward to the lunch box Hiei makes for me every day.",
						"englishNote": ""
					},
					"8": {
						"event": "Touch (Special)",
						"media": "touch_2_1",
						"chinese": "…想尝尝被书包砸的滋味吗？",
						"chineseTL": "...Do you want to be smacked by my bag?",
						"chineseNote": "",
						"japanese": "…この鞄でぶん殴られたいの？",
						"japaneseTL": "...Do you want me to hit you with my bag?",
						"japaneseNote": "",
						"english": "... Do you want me to beat you over the head with my bag?",
						"englishNote": ""
					},
					"9": {
						"event": "Flagship",
						"media": "warcry_1",
						"chinese": "唔…好像快迟到了…抓紧时间解决掉敌人吧！",
						"chineseTL": "Ah...I'm going to be late...We have to take care of the enemies quickly!",
						"chineseNote": "",
						"japanese": "くっ…時間が…早く敵をやっつけるよ！",
						"japaneseTL": "Phew, look at the time. We have to take care of the enemies quickly!",
						"japaneseNote": "",
						"english": "Shoot... No time... Let's finish them, quick!",
						"englishNote": ""
					}
				}
			}
		}
	},
	"fleet_tech": {
		"pt_get": "10",
		"add_get_attr": "HP",
		"add_get_value": "1",
		"add_get_shiptype": "Battlecruiser,Battleship,Aviation Battleship",
		"pt_upgrade": "21",
		"pt_level": "16",
		"add_level_attr": "Evasion",
		"add_level_value": "1",
		"add_level_shiptype": "Battlecruiser",
		"t_level": "3",
		"ships": "kongou,hiei,haruna,kirishima"
	}
}