{
	"name_reference" : "reno",
	"cn_reference" : "linuo",
	"nameJP" : "リノ",
	"nameCN" : "里诺",
	"ID" : "445",
	"name" : "Reno",
	"internal_id" : "102261",
	"rarity" : "Super Rare",
	"initialStar" : "★★★☆☆☆",
	"hull" : "Light Cruiser",
	"navy" : "Eagle Union",
	"prefix" : "USS",
	"buildTime" : "01:10:00",
	"parameters": {
		"firepower" : "",
		"torpedo" : "",
		"aviation" : "",
		"evasion" : "",
		"antiAir" : "",
		"hp" : ""
	},
	"scrap": {
		"gold" : "6",
		"oil" : "3",
		"medal" : "10"
	},
	"releaseDate": {
		"JP" : "March 26, 2020",
		"CN" : "March 26, 2020",
		"KR" : "March 26, 2020",
		"EN" : "March 26, 2020"
	},
	"artist": {
		"name" : "",
		"weibo" : "",
		"twitter" : "",
		"pixiv" : "",
		"other" : ""
	},
	"class" : "Atlanta-Class",
	"enhance": {
		"firepower" : "11",
		"torpedo" : "12",
		"aviation" : "0",
		"reload" : "13"
	},
	"acquisitionMethod" : "Event: Microlayer Medley",
	"skill": {
		"1" : {
			"icon" : "13120",
			"requirement" : "Default Unlocked",
			"name" : "Vigilant Supporter ",
			"type" : "Offensive",
			"description" : "At the start of the battle, if there is a CV or CVL afloat in the same fleet as this ship: increases this ship's Crit Rate by 5.0% (15.0%). For each CV or CVL in the same fleet: increases this ship's DMG to enemy DDs and CLs by 1.5% (6.0%). For the 1st and 2nd battles of each sortie that this ship takes part in: decreases DMG taken by 5.0% (10.0%) for all CVs and CVLs in the same fleet. "
		},
		"2" : {
			"icon" : "13140",
			"requirement" : "Default Unlocked",
			"name" : "Reno Reactor ",
			"type" : "Support",
			"description" : "At the start of the battle: increases this ship's AA by 5.0% (15.0%) and FP by 4.5% (12.0%). Every third time a ship in your Main Fleet takes DMG: increases this ship's AA and FP by 1.5% (6.0%) (can be stacked up to 2 times) until the end of the battle. "
		},
		"3" : {
			"icon" : "29521",
			"requirement" : "Limit Break I (III)",
			"name" : "Reno Barrage Ⅰ",
			"type" : "Offensive",
			"description" : "While equipping a DD Main Gun: increases this ship's Main Gun efficiency by 10.0%. Activates Reno Barrage Ⅰ once every 15 times (12 if equipping a DD Main Gun) the Main Guns are fired."
		}
	},
	"skin": {
		"1" : {
			"id" : "linuo",
			"name" : "Reno ",
			"description" : "Atlanta-class light cruiser – Reno, Hull Number CL-96. ",
			"expression" : {
				"0" : {
					"id" : "0"
				},
				"1" : {
					"id" : "1"
				},
				"2" : {
					"id" : "2"
				},
				"3" : {
					"id" : "3"
				},
				"4" : {
					"id" : "4"
				},
				"5" : {
					"id" : "5"
				}
			}
		},
		"2" : {
			"id" : "linuo_2",
			"name" : "Biggest Little Cheerleader",
			"description" : "This really is a huge clash of all the biggest names from all the factions. It's one exciting match after another! I gotta cheer my hardest too. Eagle Union, go get 'em!",
			"expression" : {
				"0" : {
					"id" : "0"
				},
				"1" : {
					"id" : "1"
				},
				"2" : {
					"id" : "2"
				},
				"3" : {
					"id" : "3"
				},
				"4" : {
					"id" : "4"
				}
			}
		}
	},
	"defaultEquipment": {
		"1" : {
			"icon" : "11200",
			"rarity" : "Rare",
			"name" : "Twin 127mm MK12 Dual Gun"
		},
		"2" : {
			"icon" : "",
			"rarity" : "",
			"name" : ""
		},
		"3" : {
			"icon" : "16300",
			"rarity" : "Common",
			"name" : "Twin 40mm Bofors Gun"
		}
	},
	"stats": {
		"base": {
			"hp" : "646",
			"firepower" : "27",
			"torpedo" : "36",
			"antiAir" : "93",
			"aviation" : "0",
			"reload" : "70",
			"hit" : "58",
			"evasion" : "28",
			"speed" : "32.5",
			"luck" : "52",
			"asw" : "50",
			"oxygen" : "0",
			"ammo" : "0",
			"cost" : "3",
			"armor" : "Light"
		},
		"100": {
			"hp" : "3338",
			"firepower" : "129",
			"torpedo" : "171",
			"antiAir" : "436",
			"aviation" : "0",
			"reload" : "165",
			"hit" : "150",
			"evasion" : "73",
			"speed" : "32.5",
			"luck" : "52",
			"asw" : "183",
			"oxygen" : "0",
			"ammo" : "0",
			"cost" : "11",
			"armor" : "Light"
		},
		"120": {
			"hp" : "3755",
			"firepower" : "148",
			"torpedo" : "196",
			"antiAir" : "479",
			"aviation" : "0",
			"reload" : "190",
			"hit" : "168",
			"evasion" : "95",
			"speed" : "32.5",
			"luck" : "52",
			"asw" : "203",
			"oxygen" : "0",
			"ammo" : "0",
			"cost" : "11",
			"armor" : "Light"
		},
		"100retrofit": {
			"hp" : "",
			"firepower" : "",
			"torpedo" : "",
			"antiAir" : "",
			"aviation" : "",
			"reload" : "",
			"hit" : "",
			"evasion" : "",
			"speed" : "32.5",
			"luck" : "52",
			"asw" : "",
			"oxygen" : "0",
			"ammo" : "0",
			"cost" : "11",
			"armor" : "Light"
		},
		"120retrofit": {
			"hp" : "",
			"firepower" : "",
			"torpedo" : "",
			"antiAir" : "",
			"aviation" : "",
			"reload" : "",
			"hit" : "",
			"evasion" : "",
			"speed" : "32.5",
			"luck" : "52",
			"asw" : "",
			"oxygen" : "0",
			"ammo" : "0",
			"cost" : "11",
			"armor" : "Light"
		}
	},
	"limitBreak": {
		"tier1": "Unlock EX Barrage Ⅰ/AA gun efficiency +5%",
		"tier2": "Torpedo base +1/Torpedo preload +1/AA gun efficiency +10%",
		"tier3": "Improve EX Barrage/All weapons' efficiency +5%"
	},
	"equipmentLoadout": {
		"1": {
			"type": "Destroyer Gun",
			"efficiency": "120%/120%/120%/125%",
			"amount": "1/1/1/1",
			"preload": "0/0/0/0"
		},
		"2": {
			"type": "Torpedo",
			"efficiency": "130%/130%/130%/135%",
			"amount": "1/1/2/2",
			"preload": "0/0/1/1"
		},
		"3": {
			"type": "Anti-Air Gun",
			"efficiency": "150%/155%/165%/170%",
			"amount": "1/1/1/1",
			"preload": "0/0/0/0"
		},
		"4": {
			"type": "Auxilary",
			"efficiency": "-",
			"amount": "-",
			"preload": "-"
		},
		"5": {
			"type": "Auxilary",
			"efficiency": "-",
			"amount": "-",
			"preload": "-"
		}
	},
	"fleet_tech": {
		"pt_get": "9",
		"add_get_attr": "Reload",
		"add_get_value": "1",
		"add_get_shiptype": "Light Cruiser",
		"pt_upgrade": "19",
		"pt_level": "14",
		"add_level_attr": "Anti-Air",
		"add_level_value": "2",
		"add_level_shiptype": "Light Cruiser",
		"t_level": "5",
		"ships": "atlanta,juneau,san_diego,san_juan,reno"
	},
	"build": {
		"light": {
			"JP": "",
			"CN": "",
			"EN": ""
		},
		"heavy": {
			"JP": "",
			"CN": "",
			"EN": ""
		},
		"special": {
			"JP": "",
			"CN": "",
			"EN": ""
		},
		"limited": {
			"JP": "",
			"CN": "",
			"EN": ""
		}
	},
	"drop": {
		"droppable": "false",
		"list": {
			"1": {
				"event": "",
				"chapter": {
					"1": {
						"label": "Ch .1",
						"node": {
							"1": {
								"drop": "✓",
								"note": "-"
							}
						}
					}
				}
			}
		}
	},
	"lines": {
		"skin": {
			"1": {
				"skin_id" : "linuo",
				"id" : "0",
				"label" : "Reno ",
				"dialogue" : {
					"1" : {
						"event" : "Ship Description",
						"media" : "",
						"chinese" : "亚特兰大级轻巡洋舰—里诺，舷号CL-96",
						"chineseTL" : "",
						"chineseNote" : "",
						"japanese" : "アトランタ級軽巡洋艦「リノ」（CL-96)",
						"japaneseTL" : "",
						"japaneseNote" : "",
						"english" : "Atlanta-class light cruiser – Reno, Hull Number CL-96.",
						"englishNote" : ""
					},
					"2" : {
						"event" : "Biography",
						"media" : "profile",
						"chinese" : "我是亚特兰大级的改进型，奥克兰级的里诺！相比亚特兰大级的姐姐们，我们更加专注于防空哦~虽然诞生时大战已经过半，不过也还是做了不少事呢！虽然没有救到普林斯顿是一个遗憾……总之，在这边我也会加油的，请多关照！",
						"chineseTL" : "",
						"chineseNote" : "",
						"japanese" : "アトランタ級の後期型、オークランド級のリノ。アトランタ級と比べて対空能力が更に強化されたよ。かの大戦の後半に生まれたにしては、まあ色々頑張ったよ。プリンストンのことはちょっと残念だったけど…ううん、大丈夫！これからもよろしく！",
						"japaneseTL" : "",
						"japaneseNote" : "",
						"english" : "I'm Reno, an Atlanta-class cruiser of the later Oakland subclass. We've got souped up anti-air power compared to the regular Atlanta-class. We only saw the last bits of the war, but we still fought hard. But I feel really bad about Princeton... Nnng, it's fine! We can do it!",
						"englishNote" : ""
					},
					"3" : {
						"event" : "Acquisition",
						"media" : "get",
						"chinese" : "你就是我的指挥官吗？太好了，我一直很想见你！……欸，因为指挥官就是拯救世界的超级英雄一样的存在，也就是说我就像是你的助手对吧？对了对了，我是亚特兰大级的里诺，从今往后请多指教啦~",
						"chineseTL" : "",
						"chineseNote" : "",
						"japanese" : "あなたが指揮官？ああ、実はずっと会いたかったんだ～だって指揮官、世界を救うヒーローみたいな存在でしょ？つまり私、あなたのサポーターみたいなものかな？あ、私はオークランド級のリノ、これからよろしく！",
						"japaneseTL" : "",
						"japaneseNote" : "",
						"english" : "You're the Commander? Ahh, I've always wanted to meet you! I mean, aren't people like you basically heroes trying to save the world? Which kind of makes me your sidekick, right? Oh, I'm Reno, part of the Oakland class! It's a pleasure!",
						"englishNote" : ""
					},
					"4" : {
						"event" : "Login",
						"media" : "login",
						"chinese" : "指挥官，今天也要加油拯救世界哦~",
						"chineseTL" : "",
						"chineseNote" : "",
						"japanese" : "指揮官、今日も世界を救うために頑張ってね",
						"japaneseTL" : "",
						"japaneseNote" : "",
						"english" : "Commander, today we do our best to save the world. like always!",
						"englishNote" : ""
					},
					"5" : {
						"event" : "Details",
						"media" : "detail",
						"chinese" : "唔，指挥官，这下可麻烦了呢……这个cos道具居然连明石小姐那里都找不到流通渠道，看来我只能亲自出马了",
						"chineseTL" : "",
						"chineseNote" : "",
						"japanese" : "指揮官、リノはちょっと困ってる……この衣装の小物、明石のお店でも買えなくて…もうリノが自分で作らないといけないよね、これ…",
						"japaneseTL" : "",
						"japaneseNote" : "",
						"english" : "Commander, I'm in a bit of a pickle... I can't get any of the parts for my costume at Akashi's shop... I guess I'll just have to make them myself... Hrm...",
						"englishNote" : ""
					},
					"6" : {
						"event" : "Main 1",
						"media" : "main_1",
						"chinese" : "哼哼，指挥官，你一定很在意我的手甲对吧？我跟你说哦，这个按这里能发出强光呢！还有这个按钮，它是有变形结构哦，然后然后……",
						"chineseTL" : "",
						"chineseNote" : "",
						"japanese" : "指揮官、このギアのことが気になる？実はこれ、ここを押せばこうピカーっと光ったり、ここを押せばガチャガチャっと変形したり、あとこことかこことか……",
						"japaneseTL" : "",
						"japaneseNote" : "",
						"english" : "You looking at my gear, Commander? If you press this here, it shoots out a light like bzzzzew! And if you press this one, it goes like kshaw ksshhew. And then this one's like...",
						"englishNote" : ""
					},
					"7" : {
						"event" : "Main 2",
						"media" : "main_2",
						"chinese" : "指挥官，请暂时不要管我……没事的，我没事的，我只是没有抢到想要的限量版周边而已……",
						"chineseTL" : "",
						"chineseNote" : "",
						"japanese" : "指揮官、リノはどうすれば……いや、大したことじゃないよ？ずっとほしかったあのプレミアムフィギュアが売り切れちゃって…",
						"japaneseTL" : "",
						"japaneseNote" : "",
						"english" : "Commander, I'm in a bind... Well, I guess it's not really that big a deal. It's just, I wasn't able to get this premium figure I've been wanting...",
						"englishNote" : ""
					},
					"8" : {
						"event" : "Main 3",
						"media" : "main_3",
						"chinese" : "哈……欸？啊，指挥官，不小心吵到你了吗，不好意思……我只是在想能在这么近的距离观察崇拜对象工作的样子，世上一定没有比我更幸福的助手了！",
						"chineseTL" : "",
						"chineseNote" : "",
						"japanese" : "ふぅ……ん？あ、今の邪魔だった？えへへ、サポーターとして憧れの人がこーんなに近くにいるから、つい幸せな感じになっちゃって～",
						"japaneseTL" : "",
						"japaneseNote" : "",
						"english" : "Woooww.... Hm? Oh, was I bothering you? I was just basking in the amazing feeling of a sidekick watching her hero work up close~",
						"englishNote" : ""
					},
					"9" : {
						"event" : "Touch",
						"media" : "touch_1",
						"chinese" : "欸，我做得很好吗？……呜哇啊，我我我被崇拜对象夸奖了，怎么办，好高兴，我现在脸一定超红的！",
						"chineseTL" : "",
						"chineseNote" : "",
						"japanese" : "お仕事をよくやってくれてるって？……おお！憧れの人に褒められた！リノ、今すごく恥ずかしい表情しているに違いない！",
						"japaneseTL" : "",
						"japaneseNote" : "",
						"english" : "I'm doing good work...? Oooh! My hero complimented me! Of course my face is gonna turn bright red!",
						"englishNote" : ""
					},
					"10" : {
						"event" : "Touch (Special)",
						"media" : "touch_2",
						"chinese" : "指挥官也觉得有些太大了吧？真是没办法呢……",
						"chineseTL" : "",
						"chineseNote" : "",
						"japanese" : "指揮官も大きいって思う？本当に困るよね……",
						"japaneseTL" : "",
						"japaneseNote" : "",
						"english" : "You think they're big too? They really get in the way...",
						"englishNote" : ""
					},
					"11" : {
						"event" : "Mission",
						"media" : "task",
						"chinese" : "这次下达的任务也有不少呢……不过我相信对指挥官来说都是小菜一碟~",
						"chineseTL" : "",
						"chineseNote" : "",
						"japanese" : "任務が結構あるよね…まあ、指揮官にとってはきっと大したことないに違いない！",
						"japaneseTL" : "",
						"japaneseNote" : "",
						"english" : "We got a lot to do... But I'm sure you can knock it out easy peasy, Commander!",
						"englishNote" : ""
					},
					"12" : {
						"event" : "Mission Complete",
						"media" : "mission_complete",
						"chinese" : "不愧是指挥官，这次的任务报酬也很丰盛呢！",
						"chineseTL" : "",
						"chineseNote" : "",
						"japanese" : "さっすが指揮官、いつも多くの任務報酬が手に入ってるね！",
						"japaneseTL" : "",
						"japaneseNote" : "",
						"english" : "That's my Commander! You always get the best rewards!",
						"englishNote" : ""
					},
					"13" : {
						"event" : "Mail",
						"media" : "mail",
						"chinese" : "有你的邮件哦，指挥官，会不会是粉丝信什么的呀？",
						"chineseTL" : "",
						"chineseNote" : "",
						"japanese" : "指揮官のメールだよ。もしかしてファンレターとか？",
						"japaneseTL" : "",
						"japaneseNote" : "",
						"english" : "Mail for you, Commander. Is it a fan letter?",
						"englishNote" : ""
					},
					"14" : {
						"event" : "Return to Port",
						"media" : "home",
						"chinese" : "指挥官，作战辛苦啦~来我给你擦擦汗，再喝杯水……欸？哎呀，这是作为粉丝应该做的~",
						"chineseTL" : "",
						"chineseNote" : "",
						"japanese" : "指揮官、作戦おつかれ～ほらタオルと、お飲み物と…ん？これぐらいサポーターとして当然のことじゃない？",
						"japaneseTL" : "",
						"japaneseNote" : "",
						"english" : "Good fight out there, Commander. Here's a towel and a drink... Hm? Isn't this what a sidekick does?",
						"englishNote" : ""
					},
					"15" : {
						"event" : "Commission Complete",
						"media" : "expedition",
						"chinese" : "委托组回来了哦，指挥官，一起去迎接她们吧~",
						"chineseTL" : "",
						"chineseNote" : "",
						"japanese" : "委託組が戻ってきたよ。一緒に出迎えに行こっか",
						"japaneseTL" : "",
						"japaneseNote" : "",
						"english" : "The commission came back. You want to go out and see them?",
						"englishNote" : ""
					},
					"16" : {
						"event" : "Enhancement",
						"media" : "upgrade",
						"chinese" : "哼哼，我一定会帮到指挥官的~",
						"chineseTL" : "",
						"chineseNote" : "",
						"japanese" : "ふふ、指揮官のサポートはバッチリよ！",
						"japaneseTL" : "",
						"japaneseNote" : "",
						"english" : "Hah ha! I'm the Commander's sidekick!",
						"englishNote" : ""
					},
					"17" : {
						"event" : "Flagship",
						"media" : "warcry",
						"chinese" : "防空就交给我吧！",
						"chineseTL" : "",
						"chineseNote" : "",
						"japanese" : "対空はリノにまかせて！",
						"japaneseTL" : "",
						"japaneseNote" : "",
						"english" : "Just leave the planes to me!",
						"englishNote" : ""
					},
					"18" : {
						"event" : "Victory",
						"media" : "mvp",
						"chinese" : "yeah！正义必胜~",
						"chineseTL" : "",
						"chineseNote" : "",
						"japanese" : "Yeah！正義は必ず勝つ！",
						"japaneseTL" : "",
						"japaneseNote" : "",
						"english" : "Yeah! The good guys always win!",
						"englishNote" : ""
					},
					"19" : {
						"event" : "Defeat",
						"media" : "lose",
						"chinese" : "事情在变好前，总会变得更糟……嗯，下次继续努力！",
						"chineseTL" : "",
						"chineseNote" : "",
						"japanese" : "物事はいい方向に転じる前に決まって悪い方に転ぶ――うん。つまり次から頑張ろってね",
						"japaneseTL" : "",
						"japaneseNote" : "",
						"english" : "They say it's always darkest before the dawn... Mm. We'll try harder next time.",
						"englishNote" : ""
					},
					"20" : {
						"event" : "Skill",
						"media" : "skill",
						"chinese" : "I am Reno！",
						"chineseTL" : "",
						"chineseNote" : "",
						"japanese" : "I am Reno！",
						"japaneseTL" : "",
						"japaneseNote" : "",
						"english" : "I am Reno！",
						"englishNote" : ""
					},
					"21" : {
						"event" : "Low HP",
						"media" : "hp",
						"chinese" : "看我和你们死磕到底！",
						"chineseTL" : "",
						"chineseNote" : "",
						"japanese" : "一日中でもやってやる！",
						"japaneseTL" : "",
						"japaneseNote" : "",
						"english" : "I could do this all day!",
						"englishNote" : ""
					},
					"22" : {
						"event" : "Affinity (Upset)",
						"media" : "feeling1",
						"chinese" : "原来近距离接触偶像会幻灭的说法是真的啊……唉……",
						"chineseTL" : "",
						"chineseNote" : "",
						"japanese" : "憧れのヒーローも近くから観察すると、しょうもないとことも分かるのって本当だよね……はあ……",
						"japaneseTL" : "",
						"japaneseNote" : "",
						"english" : "They say you should never meet your heroes. Now I know why... Sigh...",
						"englishNote" : ""
					},
					"23" : {
						"event" : "Affinity (Stranger)",
						"media" : "feeling2",
						"chinese" : "哼哼，我就知道指挥官对我的超级英雄装备收藏感兴趣，你看，这个是振银盾牌，这个是黑夜骑士飞镖，这是五色硬币变形腰带……哼哼，只有你想不到，没有我没有的哦！",
						"chineseTL" : "",
						"chineseNote" : "",
						"japanese" : "指揮官はリノのヒーローガジェットに興味あるよね！これイプラニウム製の盾、コウモリ印のラング、コイン付き変形ベルト…どう？指揮官が思いつきそうなのは全部揃ってるはずよ",
						"japaneseTL" : "",
						"japaneseNote" : "",
						"english" : "Commander, you're looking at my superhero gadgets! This is my Ibranium shield, this is my Chiropterang, and this here's my Worpher Belt... Cool, huh? You name it, I've got it, Commander.",
						"englishNote" : ""
					},
					"24" : {
						"event" : "Affinity (Friendly)",
						"media" : "feeling3",
						"chinese" : "以前我也有憧憬成为英雄而想锻炼自己的时候，但是这个……一点剧烈运动就会晃得很厉害……我好羡慕平胸的舰船们啊……",
						"chineseTL" : "",
						"chineseNote" : "",
						"japanese" : "リノ、スーパーヒーローに憧れて色々トレーニングしたことあるけど、これ…うん、大きすぎて激しく動くとすごく邪魔なんだ…小さい子たちを羨ましく思うよ…",
						"japaneseTL" : "",
						"japaneseNote" : "",
						"english" : "There was a time when I was training really hard to become a superhero... But these huge things got in the way of my dreams... the flat girls don't know how good they have it...",
						"englishNote" : ""
					},
					"25" : {
						"event" : "Affinity (Like)",
						"media" : "feeling4",
						"chinese" : "虽然放弃了锻炼自己，不过我还是很喜欢看各种比赛哦，我经常会和克雷文一起去当啦啦队的。对英雄们的喜爱也完全没有减少，嘻嘻，而且，为了守护所有人而努力的指挥官，我可是你的头号粉丝哦~",
						"chineseTL" : "",
						"chineseNote" : "",
						"japanese" : "トレーニングはやめちゃったけど、あのときの趣味の一つのスポーツ観戦は今も続けているよ。あ、もちろん、スポーツの試合より、ヒーローショーのほうが好き！…今はリアルヒーローの指揮官がいるからそれだけで満足かな？",
						"japaneseTL" : "",
						"japaneseNote" : "",
						"english" : "I may have given up my training, but I still love watching sports. Oh, but even more than sports, I love watching superhero shows...! But now that my real hero is here, Commander, maybe I'm good on that front.",
						"englishNote" : ""
					},
					"26" : {
						"event" : "Affinity (Love)",
						"media" : "feeling5",
						"chinese" : "虽然说“能力越大，责任越大”这句话很对，但是，英雄也好舰船也好也不是一天到晚都在战斗的嘛，指挥官也偶尔和我一样，像个普通人一样做自己喜欢做的事吧！",
						"chineseTL" : "",
						"chineseNote" : "",
						"japanese" : "力には責任が伴うというけど、まあヒーローも艦船も四六時中戦いばかりじゃないよ？たまにはリノも普通の女の子として、指揮官も普通の人として振る舞っていればいいからね？",
						"japaneseTL" : "",
						"japaneseNote" : "",
						"english" : "They say \"with great power comes great responsibility,\" but superheroes need some downtime too, just like warships. Sometimes I just gotta be a regular girl, and you're no different. Let's do something fun sometime. ",
						"englishNote" : ""
					},
					"27" : {
						"event" : "Pledge",
						"media" : "propose",
						"chinese" : "那么，从今天起，我就是指挥官的助手兼人生伴侣了~嗯嗯，虽然作为助手要做的事我已经很熟练了，不过作为人生伴侣的话……完全不知道♪要是有想让我做的事记得告诉我哦，指挥官~",
						"chineseTL" : "",
						"chineseNote" : "",
						"japanese" : "じゃあ、今日からリノは指揮官のサポーターだけでなく、人生の伴侶にもなったのね？サポートなら分かるけど、伴侶としてすべきことは…まだ分からない♪これから気になることがあったらいつでもリノに言ってね～",
						"japaneseTL" : "",
						"japaneseNote" : "",
						"english" : "So like, from now on I'm more than just your sidekick. I gotta learn how to be a partner to you too, for the rest of your life... I don't really know how to do that ♪ so you'll just have to speak up and tell me what to do~",
						"englishNote" : ""
					},
					"28" : {
						"event" : "Like Present",
						"media" : "present_like",
						"chinese" : "",
						"chineseTL" : "",
						"chineseNote" : "",
						"japanese" : "",
						"japaneseTL" : "",
						"japaneseNote" : "",
						"english" : "",
						"englishNote" : ""
					},
					"29" : {
						"event" : "Dislike Present",
						"media" : "present_dislike",
						"chinese" : "",
						"chineseTL" : "",
						"chineseNote" : "",
						"japanese" : "",
						"japaneseTL" : "",
						"japaneseNote" : "",
						"english" : "",
						"englishNote" : ""
					},
					"30" : {
						"event" : "Main Title",
						"media" : "extra",
						"chinese" : "",
						"chineseTL" : "",
						"chineseNote" : "",
						"japanese" : "",
						"japaneseTL" : "",
						"japaneseNote" : "",
						"english" : "",
						"englishNote" : ""
					}
				}
			},
			"2": {
				"skin_id" : "linuo_2",
				"id" : "1",
				"label" : "Biggest Little Cheerleader",
				"dialogue" : {
					"1" : {
						"event" : "Ship Description",
						"media" : "",
						"chinese" : "不愧是聚集了各阵营的精英们的大运动会，精彩的比赛真是一场接着一场呢！我作为啦啦队一员也要努力加油才行！白鹰，fight！",
						"chineseTL" : "",
						"chineseNote" : "",
						"japanese" : "各陣営のトップが集まる大運動会、見どころある試合が次から次へと…！うん、リノもユニオンのチアリーダーとして頑張ろう！ユニオン、ファイトぉ！",
						"japaneseTL" : "",
						"japaneseNote" : "",
						"english" : "This really is a huge clash of all the biggest names from all the factions. It's one exciting match after another! I gotta cheer my hardest too. Eagle Union, go get 'em!",
						"englishNote" : ""
					},
					"2" : {
						"event" : "Acquisition",
						"media" : "get_1",
						"chinese" : "不愧是聚集了各阵营的精英们的大运动会，精彩的比赛真是一场接着一场呢！我作为啦啦队一员也要努力加油才行！白鹰，fight！",
						"chineseTL" : "",
						"chineseNote" : "",
						"japanese" : "",
						"japaneseTL" : "",
						"japaneseNote" : "",
						"english" : "",
						"englishNote" : ""
					},
					"3" : {
						"event" : "Login",
						"media" : "login_1",
						"chinese" : "指挥官，这边看比赛的视野很好哦，来坐一会儿吧~",
						"chineseTL" : "",
						"chineseNote" : "",
						"japanese" : "",
						"japaneseTL" : "",
						"japaneseNote" : "",
						"english" : "",
						"englishNote" : ""
					},
					"4" : {
						"event" : "Details",
						"media" : "detail_1",
						"chinese" : "原本，啦啦队长应该是交给克雷文这样资历更老的白鹰舰船的，但是她却主动让给了我……为了不辜负克雷文的心意，我一定会好好为大家加油的！",
						"chineseTL" : "",
						"chineseNote" : "",
						"japanese" : "",
						"japaneseTL" : "",
						"japaneseNote" : "",
						"english" : "",
						"englishNote" : ""
					},
					"5" : {
						"event" : "Touch",
						"media" : "touch_1_1",
						"chinese" : "欸，指挥官你给我送水来了？哇哇哇，这怎么好意思！……呜呜，被偶像送水，我太幸福了……",
						"chineseTL" : "",
						"chineseNote" : "",
						"japanese" : "",
						"japaneseTL" : "",
						"japaneseNote" : "",
						"english" : "",
						"englishNote" : ""
					},
					"6" : {
						"event" : "Touch (Special)",
						"media" : "touch_2_1",
						"chinese" : "指挥官，我这里有很多人看着呢……",
						"chineseTL" : "",
						"chineseNote" : "",
						"japanese" : "",
						"japaneseTL" : "",
						"japaneseNote" : "",
						"english" : "",
						"englishNote" : ""
					},
					"7" : {
						"event" : "Mission Complete",
						"media" : "mission_complete_1",
						"chinese" : "指挥官，到颁奖时间了，大家都在等你去颁奖呢~",
						"chineseTL" : "",
						"chineseNote" : "",
						"japanese" : "",
						"japaneseTL" : "",
						"japaneseNote" : "",
						"english" : "",
						"englishNote" : ""
					},
					"8" : {
						"event" : "Return to Port",
						"media" : "home_1",
						"chinese" : "指挥官，你回来得正是时候呢，下一场比赛马上就要开始了~",
						"chineseTL" : "",
						"chineseNote" : "",
						"japanese" : "",
						"japaneseTL" : "",
						"japaneseNote" : "",
						"english" : "",
						"englishNote" : ""
					}
				}
			}
		}
	}
}
